{
  "$schema": "http://json-schema.org/draft-06/schema#",
  "title": "Schema for PP Yaml",
  "type": "object",
  "properties": {
    "configuration_paths": { 
      "type": "object",
      "properties": {
        "rose-suite": {"type": "string"},
        "rose-remap": {"type": "string"},
        "rose-regrid": {"type": "string"}
      }
    },
    "analysisLen": {"type": "string"},
    "chunk96": {"type": "string"},
    "analysisStart": {
      "type": "string",
      "format":"integer"
    },
    "analysisStop": {
      "type": "string",
      "format": "integer"
    },
    "defxyInterp": {"type": "string"},
    "rose-suite": {
      "type": "object",
      "properties": {
        "refineDiag": {
          "type":"object",
          "properties": {
            "datastager_script": {"type":"string"},
            "atmoscmip6_script": {"type":"string"}
          }
        },
        "settings": {
          "type":"object",
          "properties": {
            "history_segment": {"type":"string"},
            "pp_start": {"type":"string"},
            "pp_stop": {"type":"string"},
            "len": {"type":"string"},
            "site": {"type":"string"},
            "fre_analysis_home": {"type":["string","null"]},
            "pp_chunk_a": {"type":"string"},
            "pp_chunk_b": {"type":["string","null"]},
            "pp_grid_spec": {"type":"string"}
          }
        },
        "switches": {
          "type":"object",
          "properties": {
            "clean_work": {"type":"boolean"},
            "do_mdtf": {"type":"boolean"},
            "do_statics": {"type":"boolean"},
            "do_timeavgs": {"type":"boolean"},
            "do_refinediag": {"type":"boolean"},
            "do_atmos_plevel_masking": {"type":"boolean"},
            "do_preanalysis": {"type":"boolean"}
          }
        },
        "directories": {
          "type":"object",
          "properties": {
            "history_dir": {"type":"string"},
            "pp_dir": {"type":"string"},
            "ptmp": {"type":"string"},
            "refineDiag":{"type":"string"},
            "preanalysis":{"type":["string","null"]},
            "history_refined":{"type":"string"},
            "analysis":{"type":["string","null"]}
          }
        },
        "metadata": {
          "type":"object",
          "properties": {
            "experiment":{"type":"string"},
            "platform":{"type":"string"},
            "target":{"type":"string"}
          }
        }
      }
    },
    "regrid-remap-info": {
      "type": "object",
      "properties": {
        "component": {
          "type":"object",
          "properties": {
            "type": {"type":"string"},
            "start": {"type":"string"},
            "sources": {"type":"string"},
            "sourceGrid": {"type":"string"},
            "xyInterp": {"type":"string"},
            "zInterp": {"type":"string"},
            "interpMethod": {"type":"string"},
            "cmip": {"type":"string"},
            "timeSeries": {
              "type": "array",
              "properties": {
                "freq": {"type":"string"},
                "source": {"type":"string"},
                "chunkLength": {"type":"string"},
                "variables": {"type":"string"}
              }
            },
            "timeAverage": {
              "type": "array",
              "properties": {
                "source": {"type":"string"},
                "interval": {"type":"string"},
                "calcInterval": {"type":"string"}
              }
            }
          }
        }
      }
    },
    "tmpdir": {
      "type": "object",
      "properties": {
        "tmpdirpath": {"type":["string","null"]}
      }
    },
    "install-exp-script": {
      "type": "array",
      "properties": {
        "path": {"type": "string"},
        "install-option": {
          "type": "object",
          "properties": {
            "install": {"type": "string"}
          }
        }
      }
    }
  }
}
